{
  "fileVersion": 1,
  "fileType": "deviceInfo",
  "deviceName": "TCA Q-Eng 3&4",
  "deviceGuid": "030000004f0400000804000000000000",
  "vendorId": "0x044f",
  "productId": "0x0408",
  "productVersion": 0,
  "serialNumber": "",
  "detectedDeviceType": "Unknown",
  "numButtons": 31,
  "numHats": 0,
  "numAxes": 7,
  "numBalls": 0,
  "hasRumble": false,
  "hasTriggerRumble": false,
  "bindings": {
    "axes": {
      "leftThrottle": {
        "location": {
          "part": "mainThrottleBase",
          "placementX": "middle",
          "placementY": "top",
          "placementZ": "middle"
        },
        "y": {
          "type": "axis",
          "index": 0
        }
      },
      "rightThrottle": {
        "location": {
          "part": "mainThrottleBase",
          "placementX": "middle",
          "placementY": "top",
          "placementZ": "middle"
        },
        "y": {
          "type": "axis",
          "index": 1
        }
      },
      "rightLever": {
        "location": {
          "part": "rightLeverBase",
          "placementX": "middle",
          "placementY": "top",
          "placementZ": "middle"
        },
        "y": {
          "type": "axis",
          "index": 2
        }
      },
      "leftLever": {
        "location": {
          "part": "leftLeverBase",
          "placementX": "middle",
          "placementY": "top",
          "placementZ": "middle"
        },
        "y": {
          "type": "axis",
          "index": 5
        }
      },
      "externalPedals": {
        "optional": true,
        "leftPedal": {
          "type": "axis",
          "index": 4
        },
        "rightPedal": {
          "type": "axis",
          "index": 3
        },
        "rudder": {
          "type": "axis",
          "index": 6
        }
      }
    },
    "buttons": {
      "1": {
        "location": {
          "part": "leftThrottle",
          "placementX": "left",
          "placementY": "top",
          "placementZ": "middle"
        },
        "type": "button",
        "index": 0
      },
      "2": {
        "location": {
          "part": "rightThrottle",
          "placementX": "right",
          "placementY": "top",
          "placementZ": "middle"
        },
        "type": "button",
        "index": 1
      },
      "3": {
        "location": {
          "part": "mainThrottleBase",
          "placementX": "left",
          "placementY": "top",
          "placementZ": "front"
        },
        "type": "button",
        "index": 2
      },
      "4": {
        "location": {
          "part": "mainThrottleBase",
          "placementX": "right",
          "placementY": "top",
          "placementZ": "front"
        },
        "type": "button",
        "index": 3
      },
      "5": {
        "location": {
          "part": "mainThrottleBase",
          "placementX": "left",
          "placementY": "top",
          "placementZ": "front"
        },
        "type": "button",
        "index": 4
      },
      "6": {
        "location": {
          "part": "mainThrottleBase",
          "placementX": "right",
          "placementY": "top",
          "placementZ": "front"
        },
        "type": "button",
        "index": 5
      },
      "turningSwitchA": {
        "location": {
          "part": "mainThrottleBase",
          "placementX": "middle",
          "placementY": "top",
          "placementZ": "front"
        },
        "7": {
          "type": "button",
          "index": 6
        },
        "8": {
          "type": "button",
          "index": 7
        }
      },
      "leftThrottle": {
        "9": {
          "location": {
            "placementX": "middle",
            "placementY": "bottom",
            "placementZ": "back"
          },
          "type": "button",
          "index": 8
        },
        "10": {
          "location": {
            "placementX": "middle",
            "placementY": "bottom",
            "placementZ": "middle"
          },
          "type": "button",
          "index": 9
        },
        "11": {
          "location": {
            "placementX": "middle",
            "placementY": "bottom",
            "placementZ": "middle"
          },
          "type": "button",
          "index": 10
        },
        "12": {
          "location": {
            "placementX": "middle",
            "placementY": "bottom",
            "placementZ": "front"
          },
          "type": "button",
          "index": 11
        }
      },
      "rightThrottle": {
        "13": {
          "location": {
            "placementX": "middle",
            "placementY": "bottom",
            "placementZ": "back"
          },
          "type": "button",
          "index": 12
        },
        "14": {
          "location": {
            "placementX": "middle",
            "placementY": "bottom",
            "placementZ": "middle"
          },
          "type": "button",
          "index": 13
        },
        "15": {
          "location": {
            "placementX": "middle",
            "placementY": "bottom",
            "placementZ": "middle"
          },
          "type": "button",
          "index": 14
        },
        "16": {
          "location": {
            "placementX": "middle",
            "placementY": "bottom",
            "placementZ": "front"
          },
          "type": "button",
          "index": 15
        }
      },
      "rightLeverBase": {
        "17": {
          "location": {
            "placementX": "left",
            "placementY": "top",
            "placementZ": "front"
          },
          "type": "button",
          "index": 16
        },
        "turningSwitchB": {
          "location": {
            "placementX": "right",
            "placementY": "top",
            "placementZ": "front"
          },
          "18": {
            "type": "button",
            "index": 17
          },
          "19": {
            "type": "button",
            "index": 18
          }
        },
        "20": {
          "location": {
            "placementX": "middle",
            "placementY": "top",
            "placementZ": "front"
          },
          "type": "button",
          "index": 19
        }
      },
      "leftLeverBase": {
        "21": {
          "location": {
            "placementX": "middle",
            "placementY": "top",
            "placementZ": "front"
          },
          "type": "button",
          "index": 20
        },
        "turningSwitchC": {
          "location": {
            "placementX": "middle",
            "placementY": "top",
            "placementZ": "front"
          },
          "22": {
            "type": "button",
            "index": 21
          },
          "23": {
            "type": "button",
            "index": 22
          },
          "24": {
            "type": "button",
            "index": 23
          },
          "25": {
            "type": "button",
            "index": 24
          },
          "26": {
            "type": "button",
            "index": 25
          }
        },
        "leftLever": {
          "27": {
            "location": {
              "placementX": "middle",
              "placementY": "bottom",
              "placementZ": "back"
            },
            "type": "button",
            "index": 26
          },
          "28": {
            "location": {
              "placementX": "middle",
              "placementY": "bottom",
              "placementZ": "middle"
            },
            "type": "button",
            "index": 27
          },
          "29": {
            "location": {
              "placementX": "middle",
              "placementY": "bottom",
              "placementZ": "middle"
            },
            "type": "button",
            "index": 28
          },
          "30": {
            "location": {
              "placementX": "middle",
              "placementY": "bottom",
              "placementZ": "front"
            },
            "type": "button",
            "index": 29
          },
          "31": {
            "location": {
              "placementX": "middle",
              "placementY": "bottom",
              "placementZ": "front"
            },
            "type": "button",
            "index": 30
          }
        }
      }
    },
    "hats": {
      "pov": {
        "location": {
          "part": "mainThrottle",
          "placementX": "right",
          "placementY": "bottom",
          "placementZ": "front"
        },
        "type": "hat",
        "index": 0
      },
      "pov2": {
        "location": {
          "part": "mainThrottle",
          "placementX": "right",
          "placementY": "bottom",
          "placementZ": "front"
        },
        "type": "button",
        "indexUp": 6,
        "indexRight": 7,
        "indexDown": 8,
        "indexLeft": 9
      },
      "pov3": {
        "location": {
          "part": "mainThrottle",
          "placementX": "right",
          "placementY": "bottom",
          "placementZ": "front"
        },
        "type": "button",
        "indexUp": 10,
        "indexRight": 11,
        "indexDown": 12,
        "indexLeft": 13
      }
    }
  }
}